pyfigleet/__init__.py
pyfigleet/__main__.py
pyfigleet/test.py
pyfigleet/version.py
pyfigleet/fonts/1943____.flf
pyfigleet/fonts/3-d.flf
pyfigleet/fonts/3x5.flf
pyfigleet/fonts/4x4_offr.flf
pyfigleet/fonts/5lineoblique.flf
pyfigleet/fonts/5x7.flf
pyfigleet/fonts/5x8.flf
pyfigleet/fonts/64f1____.flf
pyfigleet/fonts/6x10.flf
pyfigleet/fonts/6x9.flf
pyfigleet/fonts/__init__.py
pyfigleet/fonts/a_zooloo.flf
pyfigleet/fonts/acrobatic.flf
pyfigleet/fonts/advenger.flf
pyfigleet/fonts/alligator.flf
pyfigleet/fonts/alligator2.flf
pyfigleet/fonts/alphabet.flf
pyfigleet/fonts/aquaplan.flf
pyfigleet/fonts/arrows.flf
pyfigleet/fonts/asc_____.flf
pyfigleet/fonts/ascii___.flf
pyfigleet/fonts/assalt_m.flf
pyfigleet/fonts/asslt__m.flf
pyfigleet/fonts/atc_____.flf
pyfigleet/fonts/atc_gran.flf
pyfigleet/fonts/avatar.flf
pyfigleet/fonts/b_m__200.flf
pyfigleet/fonts/banner.flf
pyfigleet/fonts/banner3-D.flf
pyfigleet/fonts/banner3.flf
pyfigleet/fonts/banner4.flf
pyfigleet/fonts/barbwire.flf
pyfigleet/fonts/basic.flf
pyfigleet/fonts/battle_s.flf
pyfigleet/fonts/battlesh.flf
pyfigleet/fonts/baz__bil.flf
pyfigleet/fonts/beer_pub.flf
pyfigleet/fonts/bell.flf
pyfigleet/fonts/big.flf
pyfigleet/fonts/bigchief.flf
pyfigleet/fonts/binary.flf
pyfigleet/fonts/block.flf
pyfigleet/fonts/brite.flf
pyfigleet/fonts/briteb.flf
pyfigleet/fonts/britebi.flf
pyfigleet/fonts/britei.flf
pyfigleet/fonts/broadway.flf
pyfigleet/fonts/bubble.flf
pyfigleet/fonts/bubble__.flf
pyfigleet/fonts/bubble_b.flf
pyfigleet/fonts/bulbhead.flf
pyfigleet/fonts/c1______.flf
pyfigleet/fonts/c2______.flf
pyfigleet/fonts/c_ascii_.flf
pyfigleet/fonts/c_consen.flf
pyfigleet/fonts/calgphy2.flf
pyfigleet/fonts/caligraphy.flf
pyfigleet/fonts/catwalk.flf
pyfigleet/fonts/caus_in_.flf
pyfigleet/fonts/char1___.flf
pyfigleet/fonts/char2___.flf
pyfigleet/fonts/char3___.flf
pyfigleet/fonts/char4___.flf
pyfigleet/fonts/charact1.flf
pyfigleet/fonts/charact2.flf
pyfigleet/fonts/charact3.flf
pyfigleet/fonts/charact4.flf
pyfigleet/fonts/charact5.flf
pyfigleet-0.9.post1.dist-info/LICENSE
pyfigleet-0.9.post1.dist-info/METADATA
pyfigleet-0.9.post1.dist-info/WHEEL
pyfigleet-0.9.post1.dist-info/entry_points.txt
pyfigleet-0.9.post1.dist-info/top_level.txt
pyfigleet-0.9.post1.dist-info/RECORD
